drf_excel/__init__.py
drf_excel/_version.py
drf_excel/fields.py
drf_excel/mixins.py
drf_excel/renderers.py
drf_excel/utilities.py
drf_excel-2.5.1.dist-info/LICENSE
drf_excel-2.5.1.dist-info/METADATA
drf_excel-2.5.1.dist-info/WHEEL
drf_excel-2.5.1.dist-info/top_level.txt
drf_excel-2.5.1.dist-info/RECORD
