Metadata-Version: 2.1
Name: drf-excel
Version: 2.5.1
Summary: Django REST Framework renderer for Excel spreadsheet (xlsx) files.
Author-email: Tim Allen <tallen@wharton.upenn.edu>
License: BSD-3-Clause
Project-URL: Homepage, https://github.com/wharton/drf-excel/
Project-URL: Repository, https://github.com/wharton/drf-excel/
Project-URL: Documentation, https://github.com/wharton/drf-excel/
Keywords: djangorestframework,django rest framework,excel,spreadsheet,rest,restful,api,xls,xlsx,openpyxl
Classifier: Development Status :: 5 - Production/Stable
Classifier: Environment :: Web Environment
Classifier: Intended Audience :: Developers
Classifier: License :: OSI Approved :: BSD License
Classifier: Operating System :: OS Independent
Classifier: Programming Language :: Python
Classifier: Programming Language :: Python :: 3
Classifier: Programming Language :: Python :: 3.9
Classifier: Programming Language :: Python :: 3.10
Classifier: Programming Language :: Python :: 3.11
Classifier: Programming Language :: Python :: 3.12
Classifier: Programming Language :: Python :: 3.13
Classifier: Programming Language :: Python :: 3 :: Only
Classifier: Framework :: Django
Classifier: Framework :: Django :: 4.2
Classifier: Framework :: Django :: 5.0
Classifier: Framework :: Django :: 5.1
Classifier: Topic :: Internet :: WWW/HTTP
Classifier: Topic :: Internet :: WWW/HTTP :: Dynamic Content
Requires-Python: >=3.9
License-File: LICENSE
Requires-Dist: djangorestframework>=3.14
Requires-Dist: openpyxl>=2.4
Provides-Extra: dev
Requires-Dist: django-coverage-plugin; extra == "dev"
Requires-Dist: ipython; extra == "dev"
Requires-Dist: ruff; extra == "dev"
Requires-Dist: pytest-coverage; extra == "dev"
Requires-Dist: pytest-django; extra == "dev"
